spykio/__init__.py
spykio/client.py
spykio_client-1.2.0.dist-info/licenses/LICENSE
spykio_client-1.2.0.dist-info/METADATA
spykio_client-1.2.0.dist-info/WHEEL
spykio_client-1.2.0.dist-info/top_level.txt
spykio_client-1.2.0.dist-info/RECORD
