Metadata-Version: 2.4
Name: spykio-client
Version: 1.2.0
Summary: A client library for interacting with the Spykio API.
Author: Turtle Tech BV
License: MIT
Project-URL: Homepage, https://spyk.io/
Classifier: Programming Language :: Python :: 3
Classifier: License :: OSI Approved :: MIT License
Classifier: Operating System :: OS Independent
Requires-Python: >=3.6
License-File: LICENSE
Requires-Dist: requests>=2.25.0
Dynamic: license-file
